hatch_validator/__init__.py
hatch_validator/package_validator.py
hatch_validator/core/__init__.py
hatch_validator/core/pkg_accessor_base.py
hatch_validator/core/pkg_accessor_factory.py
hatch_validator/core/validation_context.py
hatch_validator/core/validation_strategy.py
hatch_validator/core/validator_base.py
hatch_validator/core/validator_factory.py
hatch_validator/package/__init__.py
hatch_validator/package/package_service.py
hatch_validator/package/v1_1_0/__init__.py
hatch_validator/package/v1_1_0/accessor.py
hatch_validator/package/v1_1_0/dependency_validation.py
hatch_validator/package/v1_1_0/entry_point_validation.py
hatch_validator/package/v1_1_0/schema_validation.py
hatch_validator/package/v1_1_0/tools_validation.py
hatch_validator/package/v1_1_0/validator.py
hatch_validator/package/v1_2_0/__init__.py
hatch_validator/package/v1_2_0/accessor.py
hatch_validator/package/v1_2_0/dependency_validation.py
hatch_validator/package/v1_2_0/schema_validation.py
hatch_validator/package/v1_2_0/validator.py
hatch_validator/package/v1_2_1/__init__.py
hatch_validator/package/v1_2_1/accessor.py
hatch_validator/package/v1_2_1/entry_point_validation.py
hatch_validator/package/v1_2_1/schema_validation.py
hatch_validator/package/v1_2_1/tools_validation.py
hatch_validator/package/v1_2_1/validator.py
hatch_validator/package/v1_2_2/__init__.py
hatch_validator/package/v1_2_2/accessor.py
hatch_validator/package/v1_2_2/dependency_validation.py
hatch_validator/package/v1_2_2/schema_validation.py
hatch_validator/package/v1_2_2/validator.py
hatch_validator/registry/__init__.py
hatch_validator/registry/registry_accessor_base.py
hatch_validator/registry/registry_accessor_factory.py
hatch_validator/registry/registry_service.py
hatch_validator/registry/v1_1_0/__init__.py
hatch_validator/registry/v1_1_0/registry_accessor.py
hatch_validator/registry/v1_2_0/__init__.py
hatch_validator/registry/v1_2_0/registry_accessor.py
hatch_validator/schemas/__init__.py
hatch_validator-0.8.0.dist-info/licenses/LICENSE
hatch_validator-0.8.0.dist-info/METADATA
hatch_validator-0.8.0.dist-info/WHEEL
hatch_validator-0.8.0.dist-info/top_level.txt
hatch_validator-0.8.0.dist-info/RECORD
