Metadata-Version: 2.4
Name: hatch-validator
Version: 0.8.0
Summary: Package validator for Hatch packages
Author: Hatch Team
Project-URL: Homepage, https://github.com/CrackingShells/Hatch-Validator
Project-URL: Bug Tracker, https://github.com/CrackingShells/Hatch-Validator/issues
Requires-Python: >=3.7
License-File: LICENSE
Requires-Dist: jsonschema>=4.0.0
Requires-Dist: requests>=2.25.0
Requires-Dist: packaging>=20.0
Dynamic: license-file
